photonbend/__init__.py
photonbend/__main__.py
photonbend/core/__init__.py
photonbend/core/_shared.py
photonbend/core/lens.py
photonbend/core/projection.py
photonbend/core/rotation.py
photonbend/scripts/__init__.py
photonbend/scripts/commands/__init__.py
photonbend/scripts/commands/alter_photo.py
photonbend/scripts/commands/make_pano.py
photonbend/scripts/commands/make_photo.py
photonbend/scripts/main.py
photonbend/utils/__init__.py
photonbend-1.0.1.dist-info/entry_points.txt
photonbend-1.0.1.dist-info/LICENSE
photonbend-1.0.1.dist-info/WHEEL
photonbend-1.0.1.dist-info/METADATA
photonbend-1.0.1.dist-info/RECORD
