Metadata-Version: 2.1
Name: photonbend
Version: 1.0.1
Summary: Photonbend allows one to convert photos between different sorts of lenses, rotate photos and make panoramas.
License: MIT
Author: Edson Moreira
Author-email: w.moreirae@gmail.com
Requires-Python: >=3.8,<3.12
Classifier: License :: OSI Approved :: MIT License
Classifier: Programming Language :: Python :: 3
Classifier: Programming Language :: Python :: 3.8
Classifier: Programming Language :: Python :: 3.9
Classifier: Programming Language :: Python :: 3.10
Classifier: Programming Language :: Python :: 3.11
Requires-Dist: Pillow (>=9.0.1,<10.0.0)
Requires-Dist: click (>=8.0.4,<9.0.0)
Requires-Dist: numpy (>=1.22,<2.0)
Requires-Dist: scipy (>=1.8.0,<2.0.0)
